{"Body": "RAPPORT DU CONSEIL D\u2019ADMINISTRATION SUR LE GOUVERNEMENT \nD\u2019ENTREPRISE \n\n \nGGOUVERNEMENT D\u2019ENTREPPRISE  \n\n \n\n1  I  3 \n\n  \n \n\nrecevoir des rapports r\u00e9guliers du Directeur des risques de la Soci\u00e9t\u00e9 bas\u00e9 aux \u00c9tats-Unis ; \n\na) \nb)  examiner le syst\u00e8me de gestion des risques des op\u00e9rations combin\u00e9es de la Soci\u00e9t\u00e9 aux \u00c9tats-Unis (\u00ab SG\u2019s combined U.S. operations \u00bb) ; et \nc)  examiner le risque de liquidit\u00e9 de la Soci\u00e9t\u00e9 aux \u00c9tats-Unis. \n\n11.3 - Il dispose de toute information sur la situation de la Soci\u00e9t\u00e9 en mati\u00e8re de risques. Il peut recourir aux services du Directeur des \nrisques ou \u00e0 des experts ext\u00e9rieurs. \n\n11.4 - Les Commissaires aux comptes sont invit\u00e9s aux r\u00e9unions du Comit\u00e9 des risques, sauf d\u00e9cision contraire du Comit\u00e9. Ils peuvent \n\u00e9galement \u00eatre consult\u00e9s en dehors des r\u00e9unions. \n\nLe Comit\u00e9 des risques ou son Pr\u00e9sident entendent les Directeurs en charge des fonctions de contr\u00f4le interne (risque, conformit\u00e9, Audit \ninterne) ainsi que le Directeur financier et, en tant que de besoin, les cadres responsables de l'\u00e9tablissement des comptes, du contr\u00f4le \ninterne, du contr\u00f4le des risques, du contr\u00f4le de conformit\u00e9 et du contr\u00f4le p\u00e9riodique. \n\n11.5 - Le Comit\u00e9 des risques est compos\u00e9 de trois administrateurs au moins nomm\u00e9s par le Conseil d\u2019administration qui disposent de \nconnaissances,  de  comp\u00e9tences  et  d\u2019une  expertise  en  mati\u00e8re  de  risques.  Deux  tiers  au  moins  des  membres  du  Comit\u00e9  sont \nind\u00e9pendants au sens du Code AFEP-MEDEF de gouvernement d'entreprise. \n\n \n\nRAPPORT D\u2019ACTIVIT\u00c9 DU COMIT\u00c9 DES RISQUES POUR 2017 \nAu  cours  de  l\u2019exercice,  le  Comit\u00e9  des  risques  s\u2019est  r\u00e9uni  \u00e0 \n11 reprises. Le taux de pr\u00e9sence de ses membres a \u00e9t\u00e9 de 96% \n(98% en 2016). \n\nLe Comit\u00e9 des risques, \u00e0 chaque r\u00e9union, entend le Directeur des \nrisques sur l\u2019\u00e9volution du contexte de risque et les faits marquants. \nIl  examine  les  documents  relatifs  \u00e0  l\u2019app\u00e9tit  pour  le  risque  et \npr\u00e9pare les d\u00e9cisions sur l\u2019ICAAP et l\u2019ILAAP. Il fait un point r\u00e9gulier \nsur : \n(cid:374) \n(cid:374) \n\nles limites de risques pour lesquelles il pr\u00e9pare les d\u00e9cisions \ndu Conseil (en particulier, les risques de march\u00e9s) ; \n\nle panorama des risques et la cartographie des risques ; \n\n(cid:374) \n(cid:374) \n(cid:374) \n(cid:374) \n(cid:374) \n(cid:374) \n\n(cid:374) \n(cid:374) \n(cid:374) \n\nla situation de liquidit\u00e9 du Groupe ; \n\nle r\u00e9sultat d\u2019exercices de stress tests ; \n\nla Russie ; \n\nle tableau de bord de r\u00e9putation ; \n\nle tableau de bord de conformit\u00e9 ; \n\nle  tableau  de  bord  sur  les  risques  li\u00e9s  aux  syst\u00e8mes \nd\u2019information et \u00e0 leur s\u00e9curit\u00e9 ; \n\nle tableau de bord des projets r\u00e9glementaires ; \n\nles risques fiscaux ; \n\nla gestion des litiges. \n\n3\n\nEn 2017, il a consacr\u00e9 plusieurs points \u00e0 la s\u00e9curit\u00e9 informatique et \naux  syst\u00e8mes  d\u2019information.  Il  a  \u00e9t\u00e9  tenu  inform\u00e9  des  principaux \nlitiges, y compris fiscaux. Il a fait une revue de l\u2019organisation de la \nDirection  des  risques.  Il  a  \u00e9galement  revu  la  Direction  de  la \nconformit\u00e9.  Il  a  examin\u00e9  des  zones  de  risques  sp\u00e9cifiques  aux \nchantiers r\u00e9glementaires (MIFID II, etc.). Il a \u00e9galement pr\u00e9par\u00e9 les \ntravaux du Conseil sur les plans de redressement et r\u00e9solution. Il a \ndonn\u00e9 au Comit\u00e9 des r\u00e9mun\u00e9rations son avis sur la prise en compte \ndes  risques  dans  le  dispositif  de  r\u00e9mun\u00e9ration  de  la  population \nr\u00e9gul\u00e9e (professionnels des march\u00e9s et autres). \n\nIl a examin\u00e9 les risques li\u00e9s aux services financiers sp\u00e9cialis\u00e9s et \nceux li\u00e9s \u00e0 l\u2019offshoring. En juin, le Comit\u00e9, conjointement avec le \nComit\u00e9  d\u2019audit  et  de  contr\u00f4le  interne,  a  visit\u00e9  la  d\u00e9l\u00e9gation \nr\u00e9gionale  de  Soci\u00e9t\u00e9  G\u00e9n\u00e9rale  \u00e0  Lille  pour  examiner  la  mise  en \n\u0153uvre sur le terrain des dispositifs de ma\u00eetrise des risques et de \ncontr\u00f4le. En novembre, conjointement avec le Comit\u00e9 d\u2019audit et \nde  contr\u00f4le \nle  Comit\u00e9  s\u2019est  d\u00e9plac\u00e9  \u00e0  Yaound\u00e9 \n(Cameroun)  pour  s\u2019assurer  de  la  bonne  mise  en  \u0153uvre  des \ndispositifs  de  ma\u00eetrise  de  risques et  de contr\u00f4le  dans  les  filiales \nafricaines. \n\ninterne, \n\nEn tant qu\u2019US Risk Committee, le Comit\u00e9 des risques a tenu des \nr\u00e9unions  trimestrielles  pour  valider  l\u2019app\u00e9tit  pour  le  risque  des \nactivit\u00e9s am\u00e9ricaines. Il s\u2019est \u00e9galement acquitt\u00e9 des autres t\u00e2ches \npr\u00e9vues  par  la  r\u00e9glementation  am\u00e9ricaine  (supervision  du  risque \nde  liquidit\u00e9,  validation  des  politiques  de  risques,  etc.).  Il  a  suivi, \navec  le  Comit\u00e9  d\u2019audit  et  de  contr\u00f4le  interne,  les  rem\u00e9diations \ndemand\u00e9es par la FED en mati\u00e8re de suivi des risques. Le Comit\u00e9 \na  re\u00e7u  une  formation  sp\u00e9cifique  sur  ses  missions  d\u2019US Risk \nCommittee en novembre 2017. \n\n \n\n \n\nG R O U P E   S O C I \u00c9 T \u00c9   G \u00c9 N \u00c9 R AL E   I  DOCUMENT DE R\u00c9F\u00c9RENCE 2018 I 89 \n\n\f", "Chapter_title": "GOUVERNEMENT D\u2019ENTREPRISE", "Chapter_id": "3.0", "Subchapter_title": ["Rapport du Conseil dUdministrations sur le gouvernement dGntreprise"], "Subchapter_id": ["3.1"], "pdf_page": 89, "html_id": "89.html", "html_class": "", "sisters": [72, 73, 74, 75, 76, 77, 78, 79, 80, 81, 82, 83, 84, 85, 86, 87, 88, 89, 90, 91, 92, 93, 94, 95, 96, 97, 98, 99, 100, 101, 102, 103, 104, 105, 106, 107, 108, 109, 110, 111, 112, 113, 114, 115, 116, 117, 118, 119, 120, 121, 122, 123, 124, 125, 126, 127, 128, 129, 130, 131, 132], "Document": "Raport annuel societe generale 2018"}