{"Body": "6  I  6 \n\n \n\n \n\n  \n\n\u00c9\u00c9TATS FINANCIERS  \n\n \n\nNOTES ANNEXES AUX COMPTES ANNUELS \n\nNOTE 2.4 - DETTES \n\nPRINCIPES COMPTABLES \nLes dettes envers les \u00e9tablissements de cr\u00e9dit et la client\u00e8le sont ventil\u00e9es d\u2019apr\u00e8s leur dur\u00e9e initiale ou la nature de ces dettes : dettes \n\u00e0 vue (d\u00e9p\u00f4ts \u00e0 vue, comptes ordinaires) et dettes \u00e0 terme pour les \u00e9tablissements de cr\u00e9dit ; comptes d\u2019\u00e9pargne \u00e0 r\u00e9gime sp\u00e9cial et \nautres d\u00e9p\u00f4ts pour la client\u00e8le. Ces dettes int\u00e8grent les op\u00e9rations de pension, mat\u00e9rialis\u00e9es par des titres ou des valeurs, effectu\u00e9es \navec ces agents \u00e9conomiques. \n\nLes int\u00e9r\u00eats courus sur ces dettes sont port\u00e9s en comptes de dettes rattach\u00e9es en contrepartie du compte de r\u00e9sultat. \n\n1. DETTES ENVERS LES \u00c9TABLISSEMENTS DE CR\u00c9DIT \n\n \n\n \n\n(En M EUR) \n\nDettes \u00e0 vue \nD\u00e9p\u00f4ts et comptes ordinaires(1) \nValeurs donn\u00e9es en pension au jour le jour \nSous--total  \nDettes \u00e0 terme \nEmprunts et comptes \u00e0 terme(2) \nValeurs donn\u00e9es en pension \u00e0 terme \nSous--total  \nDettes rattach\u00e9es \nTotal dettes  \nTitres donn\u00e9s en pension (3) \nTotal ((4)  \n\n31.12.2017 \n\n31.12.2016 \n\n \n\n13 858 \n- \n13  858  \n \n\n158 040 \n- \n158  040  \n529 \n172  427  \n69 359 \n241  786  \n\n \n\n13 700 \n- \n13  700  \n \n\n140 869 \n- \n140  869  \n473 \n155  042  \n89 480 \n244  522  \n\n(1)  Dont 885 M EUR d\u2019op\u00e9rations vis-\u00e0-vis de Soci\u00e9t\u00e9 G\u00e9n\u00e9rale International Limited en 2016 (cf. Note 2.3). \n(2)  Dont 1 688 M EUR d\u2019op\u00e9rations vis-\u00e0-vis de Soci\u00e9t\u00e9 G\u00e9n\u00e9rale International Limited en 2016. \n(3)   Dont 12 563 M EUR d\u2019op\u00e9rations vis-\u00e0-vis de Soci\u00e9t\u00e9 G\u00e9n\u00e9rale International Limited en 2016 \n(4)   Dont dettes concernant les entreprises li\u00e9es : 77 314 M EUR au 31 d\u00e9cembre 2017 (79 158 M EUR au 31 d\u00e9cembre 2016). \n \n\n \n\n476 I DOCUMENT DE R\u00c9F\u00c9RENCE 2018 I G R O U P E   S O C I \u00c9 T \u00c9   G \u00c9 N \u00c9 R AL E  \n\n\f", "Chapter_title": "ETATS FINANCIERS", "Chapter_id": "6.0", "Subchapter_title": ["Notes annexes aux comptes annuels"], "Subchapter_id": ["6.6"], "pdf_page": 476, "html_id": "476.html", "html_class": "", "sisters": [464, 465, 466, 467, 468, 469, 470, 471, 472, 473, 474, 475, 476, 477, 478, 479, 480, 481, 482, 483, 484, 485, 486, 487, 488, 489, 490, 491, 492, 493, 494, 495, 496, 497, 498, 499, 500, 501, 502, 503, 504, 505, 506, 507, 508, 509, 510, 511, 512, 513, 514, 515, 516, 517, 518, 519, 520, 521, 522, 523], "Document": "Raport annuel societe generale 2018"}