{"Body": "6  I  2 \n\n \n\n \n\n  \n\n\u00c9\u00c9TATS FINANCIERS  \n\n \n\nNOTES ANNEXES AUX \u00c9TATS FINANCIERS CONSOLID\u00c9S \n\nNOTE 2 - CONSOLIDATION \n\n \n\n \n\nPOUR \nFAIRE \nSIMPLE \n\n \nLes diff\u00e9rentes activit\u00e9s du groupe Soci\u00e9t\u00e9 G\u00e9n\u00e9rale en France et \u00e0 l\u2019\u00e9tranger sont exerc\u00e9es par l\u2019entit\u00e9 m\u00e8re Soci\u00e9t\u00e9 \nG\u00e9n\u00e9rale (qui inclut les succursales Soci\u00e9t\u00e9 G\u00e9n\u00e9rale \u00e0 l\u2019\u00e9tranger) et par un ensemble d\u2019entit\u00e9s qu\u2019elle contr\u00f4le de \nmani\u00e8re directe ou indirecte (filiales et partenariats) ou sur lesquelles elle exerce une influence notable (entreprises \nassoci\u00e9es). Toutes ces entit\u00e9s constituent le p\u00e9rim\u00e8tre de consolidation du Groupe. \n\n \n\nLa consolidation consiste \u00e0 mettre en \u0153uvre un processus comptable norm\u00e9 pour pr\u00e9senter de mani\u00e8re agr\u00e9g\u00e9e les \ncomptes de l\u2019entit\u00e9 m\u00e8re Soci\u00e9t\u00e9 G\u00e9n\u00e9rale et de ses filiales, partenariats et entreprises associ\u00e9es, comme si elles ne \nconstituaient qu\u2019une seule et m\u00eame entit\u00e9.\n\nPour cela, les comptes individuels des entit\u00e9s composant le Groupe sont retrait\u00e9s pour \u00eatre conformes au r\u00e9f\u00e9rentiel \nIFRS tel qu\u2019adopt\u00e9 dans l\u2019Union europ\u00e9enne, afin d\u2019assurer l\u2019homog\u00e9n\u00e9it\u00e9 des donn\u00e9es pr\u00e9sent\u00e9es dans les \u00e9tats \nfinanciers consolid\u00e9s. \n\nPar ailleurs, les soldes comptables (actifs, passifs, charges et produits) g\u00e9n\u00e9r\u00e9s par des transactions entre entit\u00e9s du \nGroupe sont \u00e9limin\u00e9s lors du processus de consolidation pour ne pr\u00e9senter dans les \u00e9tats financiers consolid\u00e9s que \nles op\u00e9rations et r\u00e9sultats r\u00e9alis\u00e9s avec des tiers externes au Groupe. \n\n \n\n \n\n \n\nPRINCIPES COMPTABLES \nLes  comptes consolid\u00e9s  regroupent  les  comptes  de  Soci\u00e9t\u00e9 G\u00e9n\u00e9rale,  de  ses  succursales \u00e0  l\u2019\u00e9tranger  et  les entit\u00e9s  fran\u00e7aises  et \n\u00e9trang\u00e8res sur lesquelles le Groupe exerce un contr\u00f4le, un contr\u00f4le conjoint ou une influence notable. \n\nENTIT\u00c9S CONSOLID\u00c9ES \n(cid:374)  Filialees  \nLes filiales sont les entit\u00e9s contr\u00f4l\u00e9es de mani\u00e8re exclusive par le Groupe. Le Groupe contr\u00f4le une entit\u00e9 lorsque les conditions suivantes \nsont r\u00e9unies : \n(cid:374) \n\nle Groupe d\u00e9tient le pouvoir sur l\u2019entit\u00e9 (capacit\u00e9 de diriger ses activit\u00e9s pertinentes, \u00e0 savoir celles qui ont une incidence importante \nsur les rendements de l\u2019entit\u00e9), via la d\u00e9tention de droits de vote ou d\u2019autres droits ; et \n\nle Groupe est expos\u00e9 ou a droit \u00e0 des rendements variables en raison de ses liens avec l\u2019entit\u00e9 ; et \n\nle Groupe a la capacit\u00e9 d\u2019exercer son pouvoir sur l\u2019entit\u00e9 de mani\u00e8re \u00e0 influer sur le montant des rendements qu\u2019il en obtient. \n\n(cid:374) \n(cid:374) \nExistence du pouvoir  \n\nLe p\u00e9rim\u00e8tre des droits de vote pris en consid\u00e9ration pour appr\u00e9cier la nature du contr\u00f4le exerc\u00e9 par le Groupe sur une entit\u00e9 et les \nm\u00e9thodes  de  consolidation  applicables,  int\u00e8gre  l\u2019existence  et  l\u2019effet  de  droits  de  vote  potentiels  d\u00e8s  lors  que  ces  derniers  sont \nexer\u00e7ables \u00e0 la date d\u2019appr\u00e9ciation du contr\u00f4le ou au plus tard lorsque les d\u00e9cisions concernant la direction des activit\u00e9s pertinentes \ndoivent \u00eatre prises. Ces droits de vote potentiels peuvent provenir, par exemple, d\u2019options d\u2019achat d\u2019actions ordinaires existantes sur \nle march\u00e9 ou du droit \u00e0 convertir des obligations en actions ordinaires nouvelles. \n\nLorsque les droits de vote ne sont pas pertinents pour d\u00e9terminer l\u2019existence ou l\u2019absence de contr\u00f4le d\u2019une entit\u00e9 par le Groupe, \nl\u2019\u00e9valuation  de  ce  contr\u00f4le  doit  tenir  compte  de  tous  les  faits  et  circonstances  y  compris  l\u2019existence  d\u2019un  ou  plusieurs  accords \ncontractuels. Le pouvoir peut s\u2019exercer au travers de droits substantiels, \u00e0 savoir la capacit\u00e9 pratique de diriger les activit\u00e9s pertinentes \nde l\u2019entit\u00e9 sans obstacles ni contraintes. \n\nCertains droits ont pour but de prot\u00e9ger les int\u00e9r\u00eats de la partie qui les d\u00e9tient (droits protectifs), sans toutefois donner le pouvoir sur \nl\u2019entit\u00e9 \u00e0 laquelle les droits se rattachent. \n\nSi plusieurs investisseurs ont chacun des droits effectifs leur conf\u00e9rant la capacit\u00e9 de diriger unilat\u00e9ralement des activit\u00e9s pertinentes \ndiff\u00e9rentes, celui qui a la capacit\u00e9 effective de diriger les activit\u00e9s qui affectent le plus les rendements de l\u2019entit\u00e9, est pr\u00e9sum\u00e9 d\u00e9tenir le \npouvoir. \n\nExposition aux rendementts variables \n\nLe contr\u00f4le ne peut exister que si le Groupe est expos\u00e9 significativement \u00e0 la variabilit\u00e9 des rendements variables g\u00e9n\u00e9r\u00e9s par son \ninvestissement ou son implication dans l\u2019entit\u00e9. Les rendements variables rassemblent toutes sortes d\u2019expositions (dividendes, int\u00e9r\u00eats, \ncommissions, etc.) ; ils peuvent \u00eatre uniquement positifs, uniquement n\u00e9gatifs, ou tant\u00f4t positifs et tant\u00f4t n\u00e9gatifs. \n\n \n\n \n\n324 I DOCUMENT DE R\u00c9F\u00c9RENCE 2018 I G R O U P E   S O C I \u00c9 T \u00c9   G \u00c9 N \u00c9 R AL E  \n\n\f", "Chapter_title": "ETATS FINANCIERS", "Chapter_id": "6.0", "Subchapter_title": ["Notes annexes aux \u00e9tats financiers consolid\u00e9s"], "Subchapter_id": ["6.2"], "pdf_page": 324, "html_id": "324.html", "html_class": "", "sisters": [309, 310, 311, 312, 313, 314, 315, 316, 317, 318, 319, 320, 321, 322, 323, 324, 325, 326, 327, 328, 329, 330, 331, 332, 333, 334, 335, 336, 337, 338, 339, 340, 341, 342, 343, 344, 345, 346, 347, 348, 349, 350, 351, 352, 353, 354, 355, 356, 357, 358, 359, 360, 361, 362, 363, 364, 365, 366, 367, 368, 369, 370, 371, 372, 373, 374, 375, 376, 377, 378, 379, 380, 381, 382, 383, 384, 385, 386, 387, 388, 389, 390, 391, 392, 393, 394, 395, 396, 397, 398, 399, 400, 401, 402, 403, 404, 405, 406, 407, 408, 409, 410, 411, 412, 413, 414, 415, 416, 417, 418, 419, 420, 421, 422, 423, 424, 425, 426, 427, 428, 429, 430, 431, 432, 433, 434, 435, 436, 437, 438, 439, 440, 441, 442, 443, 444, 445, 446, 447], "Document": "Raport annuel societe generale 2018"}