{"Body": "  \n \n\nC O MP TES  A N N U ELS \n\n \n\n \n\u00c9\u00c9TATS FINANCIERS  \n\n5  I  6 \n\n5 .   C O M P T E S   A N N U E L S  \n\nBILAN SOCIAL \n\n \n\nACTIF \n\n(En M EUR) \n\nCaisse, banques centrales, comptes courants postaux \n\nEffets publics et valeurs assimil\u00e9es \n\nCr\u00e9ances sur les \u00e9tablissements de cr\u00e9dit \n\nOp\u00e9rations avec la client\u00e8le (1) \n\nObligations et autres titres \u00e0 revenu fixe \n\nActions et autres titres \u00e0 revenu variable \n\nParticipations et autres titres d\u00e9tenus \u00e0 long terme \n\nParts dans les entreprises li\u00e9es \n\nImmobilisations corporelles et incorporelles \n\nActions propres \n\nAutres actifs et comptes de r\u00e9gularisation \n\nTotal Actiif \n\n \n\n \n\n \n\n \n\nNote 2.1 \n\nNote 2.3 \n\nNote 2.3 \n\nNote 2.1 \n\nNote 2.1 \n\nNote 2.1 \n\nNote 2.1 \n\nNote 7.2 \n\nNote 2.1 \n\nNote 3.2 \n \n\n31.12.2017 \n\n31.12.2016 \n\n90 424 \n\n127 216 \n\n191 942 \n\n390 312 \n\n93 288 \n\n120 720 \n\n592 \n\n26 478 \n\n2 050 \n\n281 \n\n74 991 \n\n107 886 \n\n197 211 \n\n389 587 \n\n86 633 \n\n97 666 \n\n685 \n\n27 033 \n\n1 918 \n\n296 \n\n139 355 \n\n209 647 \n\n1  182  658  \n\n1  193  553  \n\n(1)   Les Op\u00e9rations avec la client\u00e8le incluent les op\u00e9rations de cr\u00e9dit-bail et de location assimil\u00e9es qui \u00e9taient auparavant pr\u00e9sent\u00e9es sur une ligne distincte \n\ndu bilan. \u00c0 des fins de comparabilit\u00e9, la pr\u00e9sentation des donn\u00e9es de l\u2019exercice 2016 a \u00e9t\u00e9 modifi\u00e9e par rapport aux \u00e9tats financiers publi\u00e9s. \n\nHORS-BILAN \n\n(En M EUR) \n\nEngagements de financement donn\u00e9s \n\nEngagements de garantie donn\u00e9s \n\nEngagements donn\u00e9s sur titres \n\n \n\n \n\n \n\n \n\n \n\n \n\n \n\n \n\n \n\nNote 2.3 \n\nNote 2.3 \n\n \n\n31.12.2017 \n\n31.12.2016 \n\n197 307 \n\n187 617 \n\n21 883 \n\n170 724 \n\n195 433 \n\n21 481 \n\n6\n\nG R O U P E   S O C I \u00c9 T \u00c9   G \u00c9 N \u00c9 R AL E   I  DOCUMENT DE R\u00c9F\u00c9RENCE 2018 I 461 \n\n\f", "Chapter_title": "ETATS FINANCIERS", "Chapter_id": "6.0", "Subchapter_title": ["Rapport de gestion de Soci\u00e9t\u00e9 G\u00e9n\u00e9rale"], "Subchapter_id": ["6.4"], "pdf_page": 461, "html_id": "461.html", "html_class": "", "sisters": [454, 455, 456, 457, 458, 459, 460], "Document": "Raport annuel societe generale 2018"}